dnattend/__init__.py
dnattend/cli.py
dnattend/main.py
dnattend/simulate.py
dnattend/test.py
dnattend/train.py
dnattend/utils.py
dnattend-0.2.3.dist-info/LICENSE
dnattend-0.2.3.dist-info/METADATA
dnattend-0.2.3.dist-info/WHEEL
dnattend-0.2.3.dist-info/entry_points.txt
dnattend-0.2.3.dist-info/top_level.txt
dnattend-0.2.3.dist-info/RECORD
