Metadata-Version: 2.1
Name: dnattend
Version: 0.2.3
Summary: AutoML classifier for predicting patient non-attendance (DNA)
Author: Stephen Richer
Author-email: stephen.richer@proton.me
License: MIT License
Project-URL: repository, https://github.com/nhsx/dna-risk-predict
Keywords: dnattend
Classifier: Natural Language :: English
Classifier: Intended Audience :: Science/Research
Classifier: Intended Audience :: Healthcare Industry
Classifier: Development Status :: 1 - Planning
Classifier: License :: OSI Approved :: MIT License
Classifier: Programming Language :: Python :: 3
Classifier: Programming Language :: Python :: 3.7
Classifier: Programming Language :: Python :: 3.8
Classifier: Programming Language :: Python :: 3.9
Classifier: Programming Language :: Python :: 3.10
Classifier: Programming Language :: Python :: 3.11
Requires-Python: >=3.7
License-File: LICENSE
Requires-Dist: scipy
Requires-Dist: numpy
Requires-Dist: pyyaml
Requires-Dist: pandas
Requires-Dist: joblib
Requires-Dist: seaborn
Requires-Dist: catboost
Requires-Dist: matplotlib
Requires-Dist: scikit-learn
Requires-Dist: category-encoders
Provides-Extra: shap
Requires-Dist: shap ; extra == 'shap'
